{
    "additionalProperties": true,
    "description": "Eine Zeitspanne ist definiert aus Start und/oder Ende.\nDer Unterschied zur Menge (die auch zur Abbildung von Zeitmengen genutzt wird) ist, dass konkrete Start- und Endzeitpunkte angegeben werden.\nDie Zeitspanne ist aus dem COM Zeitraum hervorgegangen, das in Zeitspanne und Menge aufgeteilt wurde.",
    "properties": {
        "_id": {
            "anyOf": [
                {
                    "type": "string"
                },
                {
                    "type": "null"
                }
            ],
            "default": null,
            "title": " Id"
        },
        "_version": {
            "anyOf": [
                {
                    "type": "string"
                },
                {
                    "type": "null"
                }
            ],
            "default": "0.6.2rc1",
            "title": " Version"
        },
        "ende": {
            "anyOf": [
                {
                    "format": "date-time",
                    "type": "string"
                },
                {
                    "type": "null"
                }
            ],
            "default": null,
            "title": "Ende"
        },
        "start": {
            "anyOf": [
                {
                    "format": "date-time",
                    "type": "string"
                },
                {
                    "type": "null"
                }
            ],
            "default": null,
            "title": "Start"
        },
        "zusatzAttribute": {
            "anyOf": [
                {
                    "items": {
                        "$ref": "https://raw.githubusercontent.com/Hochfrequenz/BO4E-Schemas/v0.6.2-rc1/src/bo4e_schemas/ZusatzAttribut.json"
                    },
                    "type": "array"
                },
                {
                    "type": "null"
                }
            ],
            "default": null,
            "title": "Zusatzattribute"
        }
    },
    "title": "Zeitspanne",
    "type": "object"
}
